{
  "id" : "updatesBeforeCheckInForm",
  "name" : "updatesBeforeCheckInForm",
  "type" : "form",
  "uuid" : "aca0c5e2-9535-4437-861b-7c0305bc6d4d",
  "modelVersion" : "2.4",
  "lastUpdate" : 1731873815779,
  "description" : "Page generated with Bonita UI designer",
  "rows" : [
    [
      {
        "type" : "container",
        "dimension" : {
          "xs" : 12
        },
        "propertyValues" : { },
        "reference" : "74a83444-d754-4b55-baf9-c55631d65e1b",
        "hasValidationError" : false,
        "id" : "pbContainer",
        "rows" : [
          [
            {
              "type" : "component",
              "dimension" : {
                "md" : 12,
                "sm" : 12,
                "xs" : 12,
                "lg" : 12
              },
              "propertyValues" : {
                "hidden" : {
                  "type" : "constant",
                  "value" : false
                },
                "level" : {
                  "type" : "constant",
                  "value" : "Level 1"
                },
                "cssClasses" : {
                  "type" : "constant",
                  "value" : ""
                },
                "text" : {
                  "type" : "interpolation",
                  "value" : "{{ task.displayName }}"
                },
                "alignment" : {
                  "type" : "constant",
                  "value" : "center"
                },
                "dimension" : {
                  "type" : "constant",
                  "value" : 12
                }
              },
              "reference" : "7b72f0ed-ca59-45d0-be42-bf20581a310a",
              "hasValidationError" : false,
              "id" : "pbTitle",
              "description" : ""
            }
          ],
          [
            {
              "type" : "component",
              "dimension" : {
                "md" : 12,
                "sm" : 12,
                "xs" : 12,
                "lg" : 12
              },
              "propertyValues" : {
                "allowHtml" : {
                  "type" : "constant",
                  "value" : true
                },
                "labelHidden" : {
                  "type" : "constant",
                  "value" : true
                },
                "hidden" : {
                  "type" : "constant",
                  "value" : false
                },
                "cssClasses" : {
                  "type" : "constant",
                  "value" : ""
                },
                "label" : {
                  "type" : "interpolation"
                },
                "text" : {
                  "type" : "interpolation",
                  "value" : "{{ task.displayDescription }}"
                },
                "alignment" : {
                  "type" : "constant",
                  "value" : "left"
                },
                "dimension" : {
                  "type" : "constant",
                  "value" : 12
                }
              },
              "reference" : "1b16c9b8-71e9-4b00-b3e8-c2dd37a035da",
              "hasValidationError" : false,
              "id" : "pbText",
              "description" : ""
            }
          ]
        ]
      }
    ],
    [
      {
        "type" : "formContainer",
        "dimension" : {
          "xs" : 12
        },
        "propertyValues" : { },
        "reference" : "5039ea08-69c0-4e5a-b371-370c6924f6fd",
        "hasValidationError" : false,
        "id" : "pbFormContainer",
        "container" : {
          "type" : "container",
          "dimension" : {
            "xs" : 12
          },
          "propertyValues" : { },
          "reference" : "b9f5e97a-07fe-4926-b202-32050b8d469e",
          "hasValidationError" : false,
          "id" : "pbContainer",
          "rows" : [
            [
              {
                "type" : "component",
                "dimension" : {
                  "md" : 12,
                  "sm" : 12,
                  "xs" : 12,
                  "lg" : 12
                },
                "propertyValues" : {
                  "hidden" : {
                    "type" : "constant",
                    "value" : false
                  },
                  "level" : {
                    "type" : "constant",
                    "value" : "Level 4"
                  },
                  "cssClasses" : {
                    "type" : "constant",
                    "value" : ""
                  },
                  "text" : {
                    "type" : "interpolation",
                    "value" : "Okr Cycle"
                  },
                  "alignment" : {
                    "type" : "constant",
                    "value" : "left"
                  },
                  "dimension" : {
                    "type" : "constant",
                    "value" : 12
                  }
                },
                "reference" : "c8c64904-7a9a-4190-a517-c6685c3b746b",
                "hasValidationError" : false,
                "id" : "pbTitle",
                "description" : ""
              }
            ],
            [
              {
                "type" : "container",
                "dimension" : {
                  "md" : 12,
                  "sm" : 12,
                  "xs" : 12,
                  "lg" : 12
                },
                "propertyValues" : {
                  "repeatedCollection" : {
                    "type" : "variable"
                  },
                  "hidden" : {
                    "type" : "constant",
                    "value" : false
                  },
                  "cssClasses" : {
                    "type" : "constant",
                    "value" : ""
                  },
                  "dimension" : {
                    "type" : "constant",
                    "value" : 12
                  }
                },
                "reference" : "35be8114-1ff2-4ab8-86a8-06daf9a922b0",
                "hasValidationError" : false,
                "id" : "pbContainer",
                "rows" : [
                  [
                    {
                      "type" : "component",
                      "dimension" : {
                        "md" : 4,
                        "sm" : 12,
                        "xs" : 12,
                        "lg" : 4
                      },
                      "propertyValues" : {
                        "labelHidden" : {
                          "type" : "constant",
                          "value" : false
                        },
                        "hidden" : {
                          "type" : "constant",
                          "value" : false
                        },
                        "labelPosition" : {
                          "type" : "constant",
                          "value" : "top"
                        },
                        "cssClasses" : {
                          "type" : "constant",
                          "value" : ""
                        },
                        "labelWidth" : {
                          "type" : "constant",
                          "value" : 1
                        },
                        "readOnly" : {
                          "type" : "constant",
                          "value" : true
                        },
                        "label" : {
                          "type" : "interpolation",
                          "value" : "Input OKR 1"
                        },
                        "placeholder" : {
                          "type" : "constant"
                        },
                        "type" : {
                          "type" : "constant",
                          "value" : "text"
                        },
                        "dimension" : {
                          "type" : "constant",
                          "value" : 12
                        },
                        "value" : {
                          "type" : "variable",
                          "value" : "okrCycle.okr_1_input"
                        },
                        "required" : {
                          "type" : "constant",
                          "value" : false
                        },
                        "allowHTML" : {
                          "type" : "constant",
                          "value" : false
                        },
                        "minLength" : {
                          "type" : "constant",
                          "value" : ""
                        },
                        "maxLength" : {
                          "type" : "constant",
                          "value" : ""
                        },
                        "debounce" : {
                          "type" : "constant",
                          "value" : 0
                        },
                        "min" : {
                          "type" : "constant"
                        },
                        "max" : {
                          "type" : "constant"
                        },
                        "step" : {
                          "type" : "constant",
                          "value" : 1
                        }
                      },
                      "reference" : "7ed93e56-0ba2-4f8b-baca-25fe90d08e42",
                      "hasValidationError" : false,
                      "id" : "pbInput",
                      "description" : ""
                    },
                    {
                      "type" : "component",
                      "dimension" : {
                        "md" : 4,
                        "sm" : 12,
                        "xs" : 12,
                        "lg" : 4
                      },
                      "propertyValues" : {
                        "labelHidden" : {
                          "type" : "constant",
                          "value" : false
                        },
                        "hidden" : {
                          "type" : "constant",
                          "value" : false
                        },
                        "labelPosition" : {
                          "type" : "constant",
                          "value" : "top"
                        },
                        "cssClasses" : {
                          "type" : "constant",
                          "value" : ""
                        },
                        "labelWidth" : {
                          "type" : "constant",
                          "value" : 1
                        },
                        "readOnly" : {
                          "type" : "constant",
                          "value" : true
                        },
                        "label" : {
                          "type" : "interpolation",
                          "value" : "Input OKR 2"
                        },
                        "placeholder" : {
                          "type" : "constant"
                        },
                        "type" : {
                          "type" : "constant",
                          "value" : "text"
                        },
                        "dimension" : {
                          "type" : "constant",
                          "value" : 12
                        },
                        "value" : {
                          "type" : "variable",
                          "value" : "okrCycle.okr_2_input"
                        },
                        "required" : {
                          "type" : "constant",
                          "value" : false
                        },
                        "allowHTML" : {
                          "type" : "constant",
                          "value" : false
                        },
                        "minLength" : {
                          "type" : "constant",
                          "value" : ""
                        },
                        "maxLength" : {
                          "type" : "constant",
                          "value" : ""
                        },
                        "debounce" : {
                          "type" : "constant",
                          "value" : 0
                        },
                        "min" : {
                          "type" : "constant"
                        },
                        "max" : {
                          "type" : "constant"
                        },
                        "step" : {
                          "type" : "constant",
                          "value" : 1
                        }
                      },
                      "reference" : "5e355d4e-fead-4421-abd1-7ab594ba272b",
                      "hasValidationError" : false,
                      "id" : "pbInput",
                      "description" : ""
                    },
                    {
                      "type" : "component",
                      "dimension" : {
                        "md" : 4,
                        "sm" : 12,
                        "xs" : 12,
                        "lg" : 4
                      },
                      "propertyValues" : {
                        "labelHidden" : {
                          "type" : "constant",
                          "value" : false
                        },
                        "hidden" : {
                          "type" : "constant",
                          "value" : false
                        },
                        "labelPosition" : {
                          "type" : "constant",
                          "value" : "top"
                        },
                        "cssClasses" : {
                          "type" : "constant",
                          "value" : ""
                        },
                        "labelWidth" : {
                          "type" : "constant",
                          "value" : 1
                        },
                        "readOnly" : {
                          "type" : "constant",
                          "value" : true
                        },
                        "label" : {
                          "type" : "interpolation",
                          "value" : "Input OKR 3"
                        },
                        "placeholder" : {
                          "type" : "constant"
                        },
                        "type" : {
                          "type" : "constant",
                          "value" : "text"
                        },
                        "dimension" : {
                          "type" : "constant",
                          "value" : 12
                        },
                        "value" : {
                          "type" : "variable",
                          "value" : "okrCycle.okr_3_input"
                        },
                        "required" : {
                          "type" : "constant",
                          "value" : false
                        },
                        "allowHTML" : {
                          "type" : "constant",
                          "value" : false
                        },
                        "minLength" : {
                          "type" : "constant",
                          "value" : ""
                        },
                        "maxLength" : {
                          "type" : "constant",
                          "value" : ""
                        },
                        "debounce" : {
                          "type" : "constant",
                          "value" : 0
                        },
                        "min" : {
                          "type" : "constant"
                        },
                        "max" : {
                          "type" : "constant"
                        },
                        "step" : {
                          "type" : "constant",
                          "value" : 1
                        }
                      },
                      "reference" : "3d781fac-99ff-41de-9c11-68388cf92bad",
                      "hasValidationError" : false,
                      "id" : "pbInput",
                      "description" : ""
                    }
                  ],
                  [
                    {
                      "type" : "component",
                      "dimension" : {
                        "md" : 4,
                        "sm" : 12,
                        "xs" : 12,
                        "lg" : 4
                      },
                      "propertyValues" : {
                        "labelHidden" : {
                          "type" : "constant",
                          "value" : false
                        },
                        "hidden" : {
                          "type" : "constant",
                          "value" : false
                        },
                        "labelPosition" : {
                          "type" : "constant",
                          "value" : "top"
                        },
                        "cssClasses" : {
                          "type" : "constant",
                          "value" : ""
                        },
                        "labelWidth" : {
                          "type" : "constant",
                          "value" : 1
                        },
                        "readOnly" : {
                          "type" : "constant",
                          "value" : true
                        },
                        "label" : {
                          "type" : "interpolation",
                          "value" : "Okr_1_output"
                        },
                        "placeholder" : {
                          "type" : "constant"
                        },
                        "type" : {
                          "type" : "constant",
                          "value" : "text"
                        },
                        "dimension" : {
                          "type" : "constant",
                          "value" : 12
                        },
                        "value" : {
                          "type" : "variable",
                          "value" : "okrCycle.okr_1_output"
                        },
                        "required" : {
                          "type" : "constant",
                          "value" : false
                        },
                        "allowHTML" : {
                          "type" : "constant",
                          "value" : false
                        },
                        "minLength" : {
                          "type" : "constant",
                          "value" : ""
                        },
                        "maxLength" : {
                          "type" : "constant",
                          "value" : ""
                        },
                        "debounce" : {
                          "type" : "constant",
                          "value" : 0
                        },
                        "min" : {
                          "type" : "constant"
                        },
                        "max" : {
                          "type" : "constant"
                        },
                        "step" : {
                          "type" : "constant",
                          "value" : 1
                        }
                      },
                      "reference" : "9bd28d4f-7e38-4129-8225-1f7d8be1652f",
                      "hasValidationError" : false,
                      "id" : "pbInput",
                      "description" : ""
                    },
                    {
                      "type" : "component",
                      "dimension" : {
                        "md" : 4,
                        "sm" : 12,
                        "xs" : 12,
                        "lg" : 4
                      },
                      "propertyValues" : {
                        "labelHidden" : {
                          "type" : "constant",
                          "value" : false
                        },
                        "hidden" : {
                          "type" : "constant",
                          "value" : false
                        },
                        "labelPosition" : {
                          "type" : "constant",
                          "value" : "top"
                        },
                        "cssClasses" : {
                          "type" : "constant",
                          "value" : ""
                        },
                        "labelWidth" : {
                          "type" : "constant",
                          "value" : 1
                        },
                        "readOnly" : {
                          "type" : "constant",
                          "value" : true
                        },
                        "label" : {
                          "type" : "interpolation",
                          "value" : "Okr_2_output"
                        },
                        "placeholder" : {
                          "type" : "constant"
                        },
                        "type" : {
                          "type" : "constant",
                          "value" : "text"
                        },
                        "dimension" : {
                          "type" : "constant",
                          "value" : 12
                        },
                        "value" : {
                          "type" : "variable",
                          "value" : "okrCycle.okr_2_output"
                        },
                        "required" : {
                          "type" : "constant",
                          "value" : false
                        },
                        "allowHTML" : {
                          "type" : "constant",
                          "value" : false
                        },
                        "minLength" : {
                          "type" : "constant",
                          "value" : ""
                        },
                        "maxLength" : {
                          "type" : "constant",
                          "value" : ""
                        },
                        "debounce" : {
                          "type" : "constant",
                          "value" : 0
                        },
                        "min" : {
                          "type" : "constant"
                        },
                        "max" : {
                          "type" : "constant"
                        },
                        "step" : {
                          "type" : "constant",
                          "value" : 1
                        }
                      },
                      "reference" : "08fbd676-a493-4d0c-952b-c5e4b2797608",
                      "hasValidationError" : false,
                      "id" : "pbInput",
                      "description" : ""
                    },
                    {
                      "type" : "component",
                      "dimension" : {
                        "md" : 4,
                        "sm" : 12,
                        "xs" : 12,
                        "lg" : 4
                      },
                      "propertyValues" : {
                        "labelHidden" : {
                          "type" : "constant",
                          "value" : false
                        },
                        "hidden" : {
                          "type" : "constant",
                          "value" : false
                        },
                        "labelPosition" : {
                          "type" : "constant",
                          "value" : "top"
                        },
                        "cssClasses" : {
                          "type" : "constant",
                          "value" : ""
                        },
                        "labelWidth" : {
                          "type" : "constant",
                          "value" : 1
                        },
                        "readOnly" : {
                          "type" : "constant",
                          "value" : true
                        },
                        "label" : {
                          "type" : "interpolation",
                          "value" : "Okr_3_output"
                        },
                        "placeholder" : {
                          "type" : "constant"
                        },
                        "type" : {
                          "type" : "constant",
                          "value" : "text"
                        },
                        "dimension" : {
                          "type" : "constant",
                          "value" : 12
                        },
                        "value" : {
                          "type" : "variable",
                          "value" : "okrCycle.okr_3_output"
                        },
                        "required" : {
                          "type" : "constant",
                          "value" : false
                        },
                        "allowHTML" : {
                          "type" : "constant",
                          "value" : false
                        },
                        "minLength" : {
                          "type" : "constant",
                          "value" : ""
                        },
                        "maxLength" : {
                          "type" : "constant",
                          "value" : ""
                        },
                        "debounce" : {
                          "type" : "constant",
                          "value" : 0
                        },
                        "min" : {
                          "type" : "constant"
                        },
                        "max" : {
                          "type" : "constant"
                        },
                        "step" : {
                          "type" : "constant",
                          "value" : 1
                        }
                      },
                      "reference" : "50bf000e-6d9b-4bc2-8598-3ad6106f04c9",
                      "hasValidationError" : false,
                      "id" : "pbInput",
                      "description" : ""
                    }
                  ],
                  [
                    {
                      "type" : "component",
                      "dimension" : {
                        "md" : 4,
                        "sm" : 12,
                        "xs" : 12,
                        "lg" : 4
                      },
                      "propertyValues" : {
                        "labelHidden" : {
                          "type" : "constant",
                          "value" : false
                        },
                        "hidden" : {
                          "type" : "constant",
                          "value" : false
                        },
                        "labelPosition" : {
                          "type" : "constant",
                          "value" : "top"
                        },
                        "cssClasses" : {
                          "type" : "constant",
                          "value" : ""
                        },
                        "labelWidth" : {
                          "type" : "constant",
                          "value" : 1
                        },
                        "readOnly" : {
                          "type" : "constant",
                          "value" : true
                        },
                        "label" : {
                          "type" : "interpolation",
                          "value" : "Okr_1_outcome"
                        },
                        "placeholder" : {
                          "type" : "constant"
                        },
                        "type" : {
                          "type" : "constant",
                          "value" : "text"
                        },
                        "dimension" : {
                          "type" : "constant",
                          "value" : 12
                        },
                        "value" : {
                          "type" : "variable",
                          "value" : "okrCycle.okr_1_outcome"
                        },
                        "required" : {
                          "type" : "constant",
                          "value" : false
                        },
                        "allowHTML" : {
                          "type" : "constant",
                          "value" : false
                        },
                        "minLength" : {
                          "type" : "constant",
                          "value" : ""
                        },
                        "maxLength" : {
                          "type" : "constant",
                          "value" : ""
                        },
                        "debounce" : {
                          "type" : "constant",
                          "value" : 0
                        },
                        "min" : {
                          "type" : "constant"
                        },
                        "max" : {
                          "type" : "constant"
                        },
                        "step" : {
                          "type" : "constant",
                          "value" : 1
                        }
                      },
                      "reference" : "368046d9-1523-4971-9ccd-47c96960b36c",
                      "hasValidationError" : false,
                      "id" : "pbInput",
                      "description" : ""
                    },
                    {
                      "type" : "component",
                      "dimension" : {
                        "md" : 4,
                        "sm" : 12,
                        "xs" : 12,
                        "lg" : 4
                      },
                      "propertyValues" : {
                        "labelHidden" : {
                          "type" : "constant",
                          "value" : false
                        },
                        "hidden" : {
                          "type" : "constant",
                          "value" : false
                        },
                        "labelPosition" : {
                          "type" : "constant",
                          "value" : "top"
                        },
                        "cssClasses" : {
                          "type" : "constant",
                          "value" : ""
                        },
                        "labelWidth" : {
                          "type" : "constant",
                          "value" : 1
                        },
                        "readOnly" : {
                          "type" : "constant",
                          "value" : true
                        },
                        "label" : {
                          "type" : "interpolation",
                          "value" : "Okr_2_outcome"
                        },
                        "placeholder" : {
                          "type" : "constant"
                        },
                        "type" : {
                          "type" : "constant",
                          "value" : "text"
                        },
                        "dimension" : {
                          "type" : "constant",
                          "value" : 12
                        },
                        "value" : {
                          "type" : "variable",
                          "value" : "okrCycle.okr_2_outcome"
                        },
                        "required" : {
                          "type" : "constant",
                          "value" : false
                        },
                        "allowHTML" : {
                          "type" : "constant",
                          "value" : false
                        },
                        "minLength" : {
                          "type" : "constant",
                          "value" : ""
                        },
                        "maxLength" : {
                          "type" : "constant",
                          "value" : ""
                        },
                        "debounce" : {
                          "type" : "constant",
                          "value" : 0
                        },
                        "min" : {
                          "type" : "constant"
                        },
                        "max" : {
                          "type" : "constant"
                        },
                        "step" : {
                          "type" : "constant",
                          "value" : 1
                        }
                      },
                      "reference" : "2894d5d6-1ea8-4a50-8468-ae73629b3c61",
                      "hasValidationError" : false,
                      "id" : "pbInput",
                      "description" : ""
                    },
                    {
                      "type" : "component",
                      "dimension" : {
                        "md" : 4,
                        "sm" : 12,
                        "xs" : 12,
                        "lg" : 4
                      },
                      "propertyValues" : {
                        "labelHidden" : {
                          "type" : "constant",
                          "value" : false
                        },
                        "hidden" : {
                          "type" : "constant",
                          "value" : false
                        },
                        "labelPosition" : {
                          "type" : "constant",
                          "value" : "top"
                        },
                        "cssClasses" : {
                          "type" : "constant",
                          "value" : ""
                        },
                        "labelWidth" : {
                          "type" : "constant",
                          "value" : 1
                        },
                        "readOnly" : {
                          "type" : "constant",
                          "value" : true
                        },
                        "label" : {
                          "type" : "interpolation",
                          "value" : "Okr_3_outcome"
                        },
                        "placeholder" : {
                          "type" : "constant"
                        },
                        "type" : {
                          "type" : "constant",
                          "value" : "text"
                        },
                        "dimension" : {
                          "type" : "constant",
                          "value" : 12
                        },
                        "value" : {
                          "type" : "variable",
                          "value" : "okrCycle.okr_3_outcome"
                        },
                        "required" : {
                          "type" : "constant",
                          "value" : false
                        },
                        "allowHTML" : {
                          "type" : "constant",
                          "value" : false
                        },
                        "minLength" : {
                          "type" : "constant",
                          "value" : ""
                        },
                        "maxLength" : {
                          "type" : "constant",
                          "value" : ""
                        },
                        "debounce" : {
                          "type" : "constant",
                          "value" : 0
                        },
                        "min" : {
                          "type" : "constant"
                        },
                        "max" : {
                          "type" : "constant"
                        },
                        "step" : {
                          "type" : "constant",
                          "value" : 1
                        }
                      },
                      "reference" : "bad57520-aade-42a4-b0b7-25233a428636",
                      "hasValidationError" : false,
                      "id" : "pbInput",
                      "description" : ""
                    }
                  ],
                  [
                    {
                      "type" : "component",
                      "dimension" : {
                        "md" : 4,
                        "sm" : 12,
                        "xs" : 12,
                        "lg" : 4
                      },
                      "propertyValues" : {
                        "labelHidden" : {
                          "type" : "constant",
                          "value" : false
                        },
                        "hidden" : {
                          "type" : "constant",
                          "value" : false
                        },
                        "labelPosition" : {
                          "type" : "constant",
                          "value" : "top"
                        },
                        "cssClasses" : {
                          "type" : "constant",
                          "value" : ""
                        },
                        "labelWidth" : {
                          "type" : "constant",
                          "value" : 1
                        },
                        "readOnly" : {
                          "type" : "constant",
                          "value" : false
                        },
                        "label" : {
                          "type" : "interpolation",
                          "value" : "Okr_1_zustaendige"
                        },
                        "placeholder" : {
                          "type" : "constant"
                        },
                        "type" : {
                          "type" : "constant",
                          "value" : "text"
                        },
                        "dimension" : {
                          "type" : "constant",
                          "value" : 12
                        },
                        "value" : {
                          "type" : "variable",
                          "value" : "okrCycle.okr_1_zustaendige"
                        },
                        "required" : {
                          "type" : "constant",
                          "value" : false
                        },
                        "allowHTML" : {
                          "type" : "constant",
                          "value" : false
                        },
                        "minLength" : {
                          "type" : "constant",
                          "value" : ""
                        },
                        "maxLength" : {
                          "type" : "constant",
                          "value" : ""
                        },
                        "debounce" : {
                          "type" : "constant",
                          "value" : 0
                        },
                        "min" : {
                          "type" : "constant"
                        },
                        "max" : {
                          "type" : "constant"
                        },
                        "step" : {
                          "type" : "constant",
                          "value" : 1
                        }
                      },
                      "reference" : "271f6a3b-1ed2-4f2a-8ebe-a4e8386eb883",
                      "hasValidationError" : false,
                      "id" : "pbInput",
                      "description" : ""
                    },
                    {
                      "type" : "component",
                      "dimension" : {
                        "md" : 4,
                        "sm" : 12,
                        "xs" : 12,
                        "lg" : 4
                      },
                      "propertyValues" : {
                        "labelHidden" : {
                          "type" : "constant",
                          "value" : false
                        },
                        "hidden" : {
                          "type" : "constant",
                          "value" : false
                        },
                        "labelPosition" : {
                          "type" : "constant",
                          "value" : "top"
                        },
                        "cssClasses" : {
                          "type" : "constant",
                          "value" : ""
                        },
                        "labelWidth" : {
                          "type" : "constant",
                          "value" : 1
                        },
                        "readOnly" : {
                          "type" : "constant",
                          "value" : false
                        },
                        "label" : {
                          "type" : "interpolation",
                          "value" : "Okr_2_zustaendige"
                        },
                        "placeholder" : {
                          "type" : "constant"
                        },
                        "type" : {
                          "type" : "constant",
                          "value" : "text"
                        },
                        "dimension" : {
                          "type" : "constant",
                          "value" : 12
                        },
                        "value" : {
                          "type" : "variable",
                          "value" : "okrCycle.okr_2_zustaendige"
                        },
                        "required" : {
                          "type" : "constant",
                          "value" : false
                        },
                        "allowHTML" : {
                          "type" : "constant",
                          "value" : false
                        },
                        "minLength" : {
                          "type" : "constant",
                          "value" : ""
                        },
                        "maxLength" : {
                          "type" : "constant",
                          "value" : ""
                        },
                        "debounce" : {
                          "type" : "constant",
                          "value" : 0
                        },
                        "min" : {
                          "type" : "constant"
                        },
                        "max" : {
                          "type" : "constant"
                        },
                        "step" : {
                          "type" : "constant",
                          "value" : 1
                        }
                      },
                      "reference" : "a9fb4c44-83d1-4aae-adf2-7d58259ffa8f",
                      "hasValidationError" : false,
                      "id" : "pbInput",
                      "description" : ""
                    },
                    {
                      "type" : "component",
                      "dimension" : {
                        "md" : 4,
                        "sm" : 12,
                        "xs" : 12,
                        "lg" : 4
                      },
                      "propertyValues" : {
                        "labelHidden" : {
                          "type" : "constant",
                          "value" : false
                        },
                        "hidden" : {
                          "type" : "constant",
                          "value" : false
                        },
                        "labelPosition" : {
                          "type" : "constant",
                          "value" : "top"
                        },
                        "cssClasses" : {
                          "type" : "constant",
                          "value" : ""
                        },
                        "labelWidth" : {
                          "type" : "constant",
                          "value" : 1
                        },
                        "readOnly" : {
                          "type" : "constant",
                          "value" : false
                        },
                        "label" : {
                          "type" : "interpolation",
                          "value" : "Okr_3_zustaendige"
                        },
                        "placeholder" : {
                          "type" : "constant"
                        },
                        "type" : {
                          "type" : "constant",
                          "value" : "text"
                        },
                        "dimension" : {
                          "type" : "constant",
                          "value" : 12
                        },
                        "value" : {
                          "type" : "variable",
                          "value" : "okrCycle.okr_3_zustaendige"
                        },
                        "required" : {
                          "type" : "constant",
                          "value" : false
                        },
                        "allowHTML" : {
                          "type" : "constant",
                          "value" : false
                        },
                        "minLength" : {
                          "type" : "constant",
                          "value" : ""
                        },
                        "maxLength" : {
                          "type" : "constant",
                          "value" : ""
                        },
                        "debounce" : {
                          "type" : "constant",
                          "value" : 0
                        },
                        "min" : {
                          "type" : "constant"
                        },
                        "max" : {
                          "type" : "constant"
                        },
                        "step" : {
                          "type" : "constant",
                          "value" : 1
                        }
                      },
                      "reference" : "91dccb93-65b2-48a0-ac12-bd47d69b1edf",
                      "hasValidationError" : false,
                      "id" : "pbInput",
                      "description" : ""
                    }
                  ],
                  [
                    {
                      "type" : "component",
                      "dimension" : {
                        "md" : 4,
                        "sm" : 12,
                        "xs" : 12,
                        "lg" : 4
                      },
                      "propertyValues" : {
                        "labelHidden" : {
                          "type" : "constant",
                          "value" : false
                        },
                        "hidden" : {
                          "type" : "constant",
                          "value" : false
                        },
                        "labelPosition" : {
                          "type" : "constant",
                          "value" : "top"
                        },
                        "cssClasses" : {
                          "type" : "constant",
                          "value" : ""
                        },
                        "labelWidth" : {
                          "type" : "constant",
                          "value" : 1
                        },
                        "readOnly" : {
                          "type" : "constant",
                          "value" : false
                        },
                        "label" : {
                          "type" : "interpolation",
                          "value" : "Okr_1_updates"
                        },
                        "placeholder" : {
                          "type" : "constant"
                        },
                        "type" : {
                          "type" : "constant",
                          "value" : "text"
                        },
                        "dimension" : {
                          "type" : "constant",
                          "value" : 12
                        },
                        "value" : {
                          "type" : "variable",
                          "value" : "okrCycle.okr_1_updates"
                        },
                        "required" : {
                          "type" : "constant",
                          "value" : false
                        },
                        "allowHTML" : {
                          "type" : "constant",
                          "value" : false
                        },
                        "minLength" : {
                          "type" : "constant",
                          "value" : ""
                        },
                        "maxLength" : {
                          "type" : "constant",
                          "value" : ""
                        },
                        "debounce" : {
                          "type" : "constant",
                          "value" : 0
                        },
                        "min" : {
                          "type" : "constant"
                        },
                        "max" : {
                          "type" : "constant"
                        },
                        "step" : {
                          "type" : "constant",
                          "value" : 1
                        }
                      },
                      "reference" : "050150c8-077d-4b24-b6bd-d9b2fbde992c",
                      "hasValidationError" : false,
                      "id" : "pbInput",
                      "description" : ""
                    },
                    {
                      "type" : "component",
                      "dimension" : {
                        "md" : 4,
                        "sm" : 12,
                        "xs" : 12,
                        "lg" : 4
                      },
                      "propertyValues" : {
                        "labelHidden" : {
                          "type" : "constant",
                          "value" : false
                        },
                        "hidden" : {
                          "type" : "constant",
                          "value" : false
                        },
                        "labelPosition" : {
                          "type" : "constant",
                          "value" : "top"
                        },
                        "cssClasses" : {
                          "type" : "constant",
                          "value" : ""
                        },
                        "labelWidth" : {
                          "type" : "constant",
                          "value" : 1
                        },
                        "readOnly" : {
                          "type" : "constant",
                          "value" : false
                        },
                        "label" : {
                          "type" : "interpolation",
                          "value" : "Okr_2_updates"
                        },
                        "placeholder" : {
                          "type" : "constant"
                        },
                        "type" : {
                          "type" : "constant",
                          "value" : "text"
                        },
                        "dimension" : {
                          "type" : "constant",
                          "value" : 12
                        },
                        "value" : {
                          "type" : "variable",
                          "value" : "okrCycle.okr_2_updates"
                        },
                        "required" : {
                          "type" : "constant",
                          "value" : false
                        },
                        "allowHTML" : {
                          "type" : "constant",
                          "value" : false
                        },
                        "minLength" : {
                          "type" : "constant",
                          "value" : ""
                        },
                        "maxLength" : {
                          "type" : "constant",
                          "value" : ""
                        },
                        "debounce" : {
                          "type" : "constant",
                          "value" : 0
                        },
                        "min" : {
                          "type" : "constant"
                        },
                        "max" : {
                          "type" : "constant"
                        },
                        "step" : {
                          "type" : "constant",
                          "value" : 1
                        }
                      },
                      "reference" : "fcc6018b-651d-4054-b19a-b842ef310c36",
                      "hasValidationError" : false,
                      "id" : "pbInput",
                      "description" : ""
                    },
                    {
                      "type" : "component",
                      "dimension" : {
                        "md" : 4,
                        "sm" : 12,
                        "xs" : 12,
                        "lg" : 4
                      },
                      "propertyValues" : {
                        "labelHidden" : {
                          "type" : "constant",
                          "value" : false
                        },
                        "hidden" : {
                          "type" : "constant",
                          "value" : false
                        },
                        "labelPosition" : {
                          "type" : "constant",
                          "value" : "top"
                        },
                        "cssClasses" : {
                          "type" : "constant",
                          "value" : ""
                        },
                        "labelWidth" : {
                          "type" : "constant",
                          "value" : 1
                        },
                        "readOnly" : {
                          "type" : "constant",
                          "value" : false
                        },
                        "label" : {
                          "type" : "interpolation",
                          "value" : "Okr_3_updates"
                        },
                        "placeholder" : {
                          "type" : "constant"
                        },
                        "type" : {
                          "type" : "constant",
                          "value" : "text"
                        },
                        "dimension" : {
                          "type" : "constant",
                          "value" : 12
                        },
                        "value" : {
                          "type" : "variable",
                          "value" : "okrCycle.okr_3_updates"
                        },
                        "required" : {
                          "type" : "constant",
                          "value" : false
                        },
                        "allowHTML" : {
                          "type" : "constant",
                          "value" : false
                        },
                        "minLength" : {
                          "type" : "constant",
                          "value" : ""
                        },
                        "maxLength" : {
                          "type" : "constant",
                          "value" : ""
                        },
                        "debounce" : {
                          "type" : "constant",
                          "value" : 0
                        },
                        "min" : {
                          "type" : "constant"
                        },
                        "max" : {
                          "type" : "constant"
                        },
                        "step" : {
                          "type" : "constant",
                          "value" : 1
                        }
                      },
                      "reference" : "e12300ec-8e4a-4e31-a475-fcc65a241003",
                      "hasValidationError" : false,
                      "id" : "pbInput",
                      "description" : ""
                    }
                  ],
                  [
                    {
                      "type" : "component",
                      "dimension" : {
                        "md" : 12,
                        "sm" : 12,
                        "xs" : 12,
                        "lg" : 12
                      },
                      "propertyValues" : {
                        "allowHtml" : {
                          "type" : "constant",
                          "value" : true
                        },
                        "labelHidden" : {
                          "type" : "constant",
                          "value" : false
                        },
                        "hidden" : {
                          "type" : "expression",
                          "value" : "!okrCycle.check_in_counter"
                        },
                        "cssClasses" : {
                          "type" : "constant",
                          "value" : ""
                        },
                        "label" : {
                          "type" : "interpolation",
                          "value" : "Check_in_counter"
                        },
                        "text" : {
                          "type" : "interpolation",
                          "value" : "{{okrCycle.check_in_counter}}"
                        },
                        "alignment" : {
                          "type" : "constant",
                          "value" : "left"
                        },
                        "dimension" : {
                          "type" : "constant",
                          "value" : 12
                        },
                        "allowHTML" : {
                          "type" : "constant",
                          "value" : false
                        },
                        "labelPosition" : {
                          "type" : "constant",
                          "value" : "top"
                        },
                        "labelWidth" : {
                          "type" : "constant",
                          "value" : 4
                        }
                      },
                      "reference" : "a0a8deab-a53e-49ee-a433-841b47d51943",
                      "hasValidationError" : false,
                      "id" : "pbText",
                      "description" : ""
                    }
                  ]
                ]
              }
            ],
            [
              {
                "type" : "component",
                "dimension" : {
                  "md" : 12,
                  "sm" : 12,
                  "xs" : 12,
                  "lg" : 12
                },
                "propertyValues" : {
                  "removeItem" : {
                    "type" : "variable"
                  },
                  "hidden" : {
                    "type" : "constant",
                    "value" : false
                  },
                  "cssClasses" : {
                    "type" : "constant",
                    "value" : ""
                  },
                  "buttonStyle" : {
                    "type" : "constant",
                    "value" : "primary"
                  },
                  "label" : {
                    "type" : "interpolation",
                    "value" : "Aufgabe beenden"
                  },
                  "dataToSend" : {
                    "type" : "expression",
                    "value" : "formOutput"
                  },
                  "dataFromError" : {
                    "type" : "variable",
                    "value" : "formOutput._submitError"
                  },
                  "allowHTML" : {
                    "type" : "constant",
                    "value" : false
                  },
                  "labelHidden" : {
                    "type" : "constant",
                    "value" : false
                  },
                  "collectionPosition" : {
                    "type" : "constant"
                  },
                  "targetUrlOnSuccess" : {
                    "type" : "interpolation",
                    "value" : "/bonita"
                  },
                  "action" : {
                    "type" : "constant",
                    "value" : "Submit task"
                  },
                  "collectionToModify" : {
                    "type" : "variable"
                  },
                  "valueToAdd" : {
                    "type" : "expression"
                  },
                  "disabled" : {
                    "type" : "expression",
                    "value" : "$form.$invalid"
                  },
                  "alignment" : {
                    "type" : "constant",
                    "value" : "center"
                  },
                  "dimension" : {
                    "type" : "constant",
                    "value" : 12
                  },
                  "assign" : {
                    "type" : "constant",
                    "value" : false
                  },
                  "url" : {
                    "type" : "interpolation"
                  },
                  "responseStatusCode" : {
                    "type" : "variable"
                  },
                  "dataFromSuccess" : {
                    "type" : "variable"
                  },
                  "closeOnSuccess" : {
                    "type" : "constant",
                    "value" : false
                  },
                  "modalId" : {
                    "type" : "constant",
                    "value" : ""
                  }
                },
                "reference" : "8803c092-044d-42d4-8cfe-a5cb1491848b",
                "hasValidationError" : false,
                "id" : "pbButton",
                "description" : ""
              }
            ],
            [
              {
                "type" : "component",
                "dimension" : {
                  "md" : 12,
                  "sm" : 12,
                  "xs" : 12,
                  "lg" : 12
                },
                "propertyValues" : {
                  "allowHTML" : {
                    "type" : "constant",
                    "value" : true
                  },
                  "allowHtml" : {
                    "type" : "constant",
                    "value" : true
                  },
                  "labelHidden" : {
                    "type" : "constant",
                    "value" : true
                  },
                  "hidden" : {
                    "type" : "expression",
                    "value" : "!formOutput._submitError.message"
                  },
                  "cssClasses" : {
                    "type" : "constant",
                    "value" : "alert alert-danger col-lg-6 col-lg-offset-3"
                  },
                  "label" : {
                    "type" : "interpolation"
                  },
                  "text" : {
                    "type" : "interpolation",
                    "value" : "<strong>Debug message</strong>\n<br/>\n{{formOutput._submitError.message}}\n{{submit_errors_list}}"
                  },
                  "alignment" : {
                    "type" : "constant",
                    "value" : "left"
                  },
                  "dimension" : {
                    "type" : "constant",
                    "value" : 12
                  }
                },
                "reference" : "ec78747b-cd63-4476-8401-2002305e6da0",
                "hasValidationError" : false,
                "id" : "pbText",
                "description" : ""
              }
            ]
          ]
        }
      }
    ]
  ],
  "variables" : {
    "task" : {
      "type" : "url",
      "value" : [
        "../API/bpm/userTask/{{taskId}}"
      ],
      "exposed" : false
    },
    "submit_errors_list" : {
      "type" : "expression",
      "value" : [
        "if($data.formOutput && $data.formOutput._submitError && $data.formOutput._submitError.explanations){",
        "\tconst liElements = $data.formOutput._submitError.explanations",
        "\t\t.filter(cause => cause !== null)",
        "\t\t.map(cause => \"<li>\" + cause + \"</li>\")",
        "\t\t.join('');",
        "\tif(liElements){",
        "\t\treturn \"<ul>\" + liElements + \"</ul>\";",
        "\t}",
        "}"
      ],
      "exposed" : false
    },
    "formOutput" : {
      "type" : "expression",
      "value" : [
        "if( $data.okrCycle ){",
        "\treturn {",
        "\t\t//map okrCycle variable to expected task contract input",
        "\t\tokrCycleInput: {",
        "\t\t\tokr_1_input: $data.okrCycle.okr_1_input !== undefined ? $data.okrCycle.okr_1_input : null,",
        "\t\t\tokr_1_output: $data.okrCycle.okr_1_output !== undefined ? $data.okrCycle.okr_1_output : null,",
        "\t\t\tokr_1_outcome: $data.okrCycle.okr_1_outcome !== undefined ? $data.okrCycle.okr_1_outcome : null,",
        "\t\t\tokr_2_input: $data.okrCycle.okr_2_input !== undefined ? $data.okrCycle.okr_2_input : null,",
        "\t\t\tokr_2_output: $data.okrCycle.okr_2_output !== undefined ? $data.okrCycle.okr_2_output : null,",
        "\t\t\tokr_2_outcome: $data.okrCycle.okr_2_outcome !== undefined ? $data.okrCycle.okr_2_outcome : null,",
        "\t\t\tokr_3_input: $data.okrCycle.okr_3_input !== undefined ? $data.okrCycle.okr_3_input : null,",
        "\t\t\tokr_3_output: $data.okrCycle.okr_3_output !== undefined ? $data.okrCycle.okr_3_output : null,",
        "\t\t\tokr_3_outcome: $data.okrCycle.okr_3_outcome !== undefined ? $data.okrCycle.okr_3_outcome : null,",
        "\t\t\tokr_1_zustaendige: $data.okrCycle.okr_1_zustaendige !== undefined ? $data.okrCycle.okr_1_zustaendige : null,",
        "\t\t\tokr_2_zustaendige: $data.okrCycle.okr_2_zustaendige !== undefined ? $data.okrCycle.okr_2_zustaendige : null,",
        "\t\t\tokr_3_zustaendige: $data.okrCycle.okr_3_zustaendige !== undefined ? $data.okrCycle.okr_3_zustaendige : null,",
        "\t\t\tokr_1_updates: $data.okrCycle.okr_1_updates !== undefined ? $data.okrCycle.okr_1_updates : null,",
        "\t\t\tokr_1_erfuellungsgrad: $data.okrCycle.okr_1_erfuellungsgrad !== undefined ? $data.okrCycle.okr_1_erfuellungsgrad : null,",
        "\t\t\tokr_1_entscheidung: $data.okrCycle.okr_1_entscheidung !== undefined ? $data.okrCycle.okr_1_entscheidung : null,",
        "\t\t\tokr_2_updates: $data.okrCycle.okr_2_updates !== undefined ? $data.okrCycle.okr_2_updates : null,",
        "\t\t\tokr_2_erfuellungsgrad: $data.okrCycle.okr_2_erfuellungsgrad !== undefined ? $data.okrCycle.okr_2_erfuellungsgrad : null,",
        "\t\t\tokr_2_entscheidung: $data.okrCycle.okr_2_entscheidung !== undefined ? $data.okrCycle.okr_2_entscheidung : null,",
        "\t\t\tokr_3_updates: $data.okrCycle.okr_3_updates !== undefined ? $data.okrCycle.okr_3_updates : null,",
        "\t\t\tokr_3_erfuellungsgrad: $data.okrCycle.okr_3_erfuellungsgrad !== undefined ? $data.okrCycle.okr_3_erfuellungsgrad : null,",
        "\t\t\tokr_3_entscheidung: $data.okrCycle.okr_3_entscheidung !== undefined ? $data.okrCycle.okr_3_entscheidung : null",
        "\t\t}",
        "\t}",
        "}"
      ],
      "exposed" : false
    },
    "context" : {
      "type" : "url",
      "value" : [
        "../API/bpm/userTask/{{taskId}}/context"
      ],
      "exposed" : false
    },
    "taskId" : {
      "type" : "urlparameter",
      "value" : [
        "id"
      ],
      "exposed" : false
    },
    "okrCycle" : {
      "type" : "url",
      "value" : [
        "../{{context.okrCycle_ref.link}}"
      ],
      "exposed" : false
    }
  },
  "assets" : [
    {
      "id" : "e8656de8-dd41-49fa-addc-205696b8b1ee",
      "name" : "localization.json",
      "type" : "json",
      "order" : 0,
      "external" : false
    },
    {
      "id" : "87a1a369-9157-41e9-a937-8d415c1cf43a",
      "name" : "style.css",
      "type" : "css",
      "order" : 0,
      "external" : false
    }
  ],
  "inactiveAssets" : [ ],
  "webResources" : [ ],
  "hasValidationError" : false
}